{
  "questions": {
    "4GUvpqBBImcLmN2eh1HK": 3,
    "8aIrKLvItXrwvOHq1L34": 2,
    "9Hg8tuMRdMTuVY7OZ9HL": 6,
    "9WTotPoDW5OuWxsCf4Li": 3,
    "DlT19snCttf5j5RUAXLz": 3,
    "JnFbEQt0uA8RSEuy22SQ": 9,
    "JU0iGKNhR7NQzA8M77vt": 3,
    "onwrfsH02TgIhlyRUh56": 3,
    "xQWHl1hBYAKM96X4deR8": 2,
    "GUNCEL_BM_KURULUS": 1,
    "MAT_TEMEL_KAVRAMLAR": 1,
    "MAT_BOLUNEEBILME": 1,
    "MAT_ASAL_EBOB_EKOK": 1,
    "MAT_ESITSIZLIK_MUTLAK": 1,
    "MAT_USLU_SAYILAR": 1,
    "MAT_KOKLU_SAYILAR": 1,
    "MAT_DENKLEM_PROBLEMLER": 1,
    "MAT_KUMELER": 1,
    "MAT_FONKSIYONLAR": 2,
    "MAT_PERMUTASYON_KOMBINASYON": 1,
    "MAT_ORUNTU_PROBLEMLERI": 1,
    "JmyiPxf3n96Jkxqsa9jY": 2,
    "AJNLHhhaG2SLWOvxDYqW": 2,
    "nN8JOTR7LZm01AN2i3sQ": 3,
    "jXcsrl5HEb65DmfpfqqI": 4,
    "qSEqigIsIEBAkhcMTyCE": 3,
    "wnt2zWaV1pX8p8s8BBc9": 1,
    "1FEcPsGduhjcQARpaGBk": 3,
    "kbs0Ffved9pCP3Hq9M9k": 3,
    "6e0Thsz2RRNHFcwqQXso": 3,
    "uYDrMlBCEAho5776WZi8": 1,
    "WxrtQ26p2My4uJa0h1kk": 1,
    "GdpN8uxJNGtexWrkoL1T": 1,
    "AQ0Zph76dzPdr87H1uKa": 1,
    "n4OjWupHmouuybQzQ1Fc": 1,
    "xXGXiqx2TkCtI4C7GMQg": 1,
    "1JZAYECyEn7farNNyGyx": 1,
    "lv93cmhwq7RmOFM5WxWD": 1,
    "Bo3qqooJsqtIZrK5zc9S": 1,
    "80e0wkTLvaTQzPD6puB7": 1,
    "yWlh5C6jB7lzuJOodr2t": 1,
    "ICNDiSlTmmjWEQPT6rmT": 2
  },
  "flashcards": {
    "1FEcPsGduhjcQARpaGBk": 2,
    "1JZAYECyEn7farNNyGyx": 2,
    "4GUvpqBBImcLmN2eh1HK": 2,
    "6e0Thsz2RRNHFcwqQXso": 2,
    "80e0wkTLvaTQzPD6puB7": 2,
    "9Hg8tuMRdMTuVY7OZ9HL": 2,
    "AJNLHhhaG2SLWOvxDYqW": 2,
    "AQ0Zph76dzPdr87H1uKa": 2,
    "Bo3qqooJsqtIZrK5zc9S": 2,
    "DlT19snCttf5j5RUAXLz": 2,
    "GdpN8uxJNGtexWrkoL1T": 2,
    "ICNDiSlTmmjWEQPT6rmT": 2,
    "JmyiPxf3n96Jkxqsa9jY": 2,
    "JnFbEQt0uA8RSEuy22SQ": 2,
    "jXcsrl5HEb65DmfpfqqI": 2,
    "kbs0Ffved9pCP3Hq9M9k": 2,
    "lv93cmhwq7RmOFM5WxWD": 2,
    "n4OjWupHmouuybQzQ1Fc": 2,
    "nN8JOTR7LZm01AN2i3sQ": 2,
    "onwrfsH02TgIhlyRUh56": 2,
    "qBFhnVl9E4oNj8MsBqnB": 1,
    "qSEqigIsIEBAkhcMTyCE": 2,
    "rl2xQTfv1iUaCyhFzp5V": 1,
    "uYDrMlBCEAho5776WZi8": 2,
    "wnt2zWaV1pX8p8s8BBc9": 2,
    "WxrtQ26p2My4uJa0h1kk": 2,
    "xQWHl1hBYAKM96X4deR8": 2,
    "xXGXiqx2TkCtI4C7GMQg": 2,
    "yWlh5C6jB7lzuJOodr2t": 2,
    "8aIrKLvItXrwvOHq1L34": 2,
    "GUNCEL_BM_KURULUS": 2,
    "GUNCEL_NATO_AB": 2,
    "GUNCEL_BOLGESEL_KURULUS": 2,
    "JU0iGKNhR7NQzA8M77vt": 2,
    "9WTotPoDW5OuWxsCf4Li": 2,
    "GUNCEL_TURKIYE_KURULUS": 1,
    "GUNCEL_ONEMLI_TARIHLER": 1,
    "MAT_TEMEL_KAVRAMLAR": 1,
    "MAT_BOLUNEEBILME": 1,
    "MAT_ASAL_EBOB_EKOK": 1,
    "MAT_RASYONEL_SAYILAR": 1,
    "MAT_ESITSIZLIK_MUTLAK": 1,
    "MAT_USLU_SAYILAR": 1,
    "MAT_KOKLU_SAYILAR": 1,
    "MAT_ORAN_ORANTI": 1,
    "MAT_DENKLEM_PROBLEMLER": 1,
    "MAT_KUMELER": 1,
    "MAT_FONKSIYONLAR": 1,
    "MAT_PERMUTASYON_KOMBINASYON": 1,
    "MAT_OLASILIK_ISTATISTIK": 1,
    "MAT_ORUNTU_PROBLEMLERI": 1
  },
  "stories": {
    "JnFbEQt0uA8RSEuy22SQ": 4,
    "9Hg8tuMRdMTuVY7OZ9HL": 2,
    "8aIrKLvItXrwvOHq1L34": 2,
    "JU0iGKNhR7NQzA8M77vt": 2,
    "9WTotPoDW5OuWxsCf4Li": 3,
    "DlT19snCttf5j5RUAXLz": 2,
    "4GUvpqBBImcLmN2eh1HK": 2,
    "onwrfsH02TgIhlyRUh56": 2,
    "xQWHl1hBYAKM96X4deR8": 2,
    "80e0wkTLvaTQzPD6puB7": 2,
    "yWlh5C6jB7lzuJOodr2t": 2,
    "ICNDiSlTmmjWEQPT6rmT": 2,
    "JmyiPxf3n96Jkxqsa9jY": 2,
    "AJNLHhhaG2SLWOvxDYqW": 2,
    "nN8JOTR7LZm01AN2i3sQ": 2,
    "jXcsrl5HEb65DmfpfqqI": 2,
    "qSEqigIsIEBAkhcMTyCE": 2,
    "wnt2zWaV1pX8p8s8BBc9": 2,
    "1FEcPsGduhjcQARpaGBk": 2,
    "kbs0Ffved9pCP3Hq9M9k": 2,
    "6e0Thsz2RRNHFcwqQXso": 2,
    "uYDrMlBCEAho5776WZi8": 2,
    "WxrtQ26p2My4uJa0h1kk": 2,
    "GdpN8uxJNGtexWrkoL1T": 2,
    "AQ0Zph76dzPdr87H1uKa": 2,
    "n4OjWupHmouuybQzQ1Fc": 2,
    "xXGXiqx2TkCtI4C7GMQg": 2,
    "1JZAYECyEn7farNNyGyx": 2,
    "lv93cmhwq7RmOFM5WxWD": 2,
    "Bo3qqooJsqtIZrK5zc9S": 2,
    "GUNCEL_BM_KURULUS": 2,
    "GUNCEL_NATO_AB": 2,
    "GUNCEL_BOLGESEL_KURULUS": 2,
    "GUNCEL_TURKIYE_KURULUS": 2,
    "GUNCEL_ONEMLI_TARIHLER": 2,
    "MAT_TEMEL_KAVRAMLAR": 2,
    "MAT_BOLUNEEBILME": 2,
    "MAT_ASAL_EBOB_EKOK": 3,
    "MAT_RASYONEL_SAYILAR": 2,
    "MAT_ESITSIZLIK_MUTLAK": 2,
    "MAT_USLU_SAYILAR": 2,
    "MAT_KOKLU_SAYILAR": 2,
    "MAT_ORAN_ORANTI": 2,
    "MAT_DENKLEM_PROBLEMLER": 3,
    "MAT_KUMELER": 2,
    "MAT_FONKSIYONLAR": 2,
    "MAT_PERMUTASYON_KOMBINASYON": 2,
    "MAT_OLASILIK_ISTATISTIK": 2,
    "MAT_ORUNTU_PROBLEMLERI": 3
  },
  "explanations": {
    "JnFbEQt0uA8RSEuy22SQ": 5,
    "9Hg8tuMRdMTuVY7OZ9HL": 4,
    "8aIrKLvItXrwvOHq1L34": 5,
    "JU0iGKNhR7NQzA8M77vt": 5,
    "9WTotPoDW5OuWxsCf4Li": 6,
    "DlT19snCttf5j5RUAXLz": 4,
    "4GUvpqBBImcLmN2eh1HK": 4,
    "onwrfsH02TgIhlyRUh56": 4,
    "xQWHl1hBYAKM96X4deR8": 4,
    "80e0wkTLvaTQzPD6puB7": 4,
    "yWlh5C6jB7lzuJOodr2t": 4,
    "ICNDiSlTmmjWEQPT6rmT": 4,
    "JmyiPxf3n96Jkxqsa9jY": 5,
    "AJNLHhhaG2SLWOvxDYqW": 4,
    "nN8JOTR7LZm01AN2i3sQ": 4,
    "jXcsrl5HEb65DmfpfqqI": 4,
    "qSEqigIsIEBAkhcMTyCE": 4,
    "wnt2zWaV1pX8p8s8BBc9": 4,
    "1FEcPsGduhjcQARpaGBk": 4,
    "kbs0Ffved9pCP3Hq9M9k": 4,
    "6e0Thsz2RRNHFcwqQXso": 4,
    "uYDrMlBCEAho5776WZi8": 4,
    "WxrtQ26p2My4uJa0h1kk": 4,
    "GdpN8uxJNGtexWrkoL1T": 4,
    "AQ0Zph76dzPdr87H1uKa": 4,
    "n4OjWupHmouuybQzQ1Fc": 4,
    "xXGXiqx2TkCtI4C7GMQg": 4,
    "1JZAYECyEn7farNNyGyx": 4,
    "lv93cmhwq7RmOFM5WxWD": 4,
    "Bo3qqooJsqtIZrK5zc9S": 4,
    "GUNCEL_BM_KURULUS": 4,
    "GUNCEL_NATO_AB": 4,
    "GUNCEL_BOLGESEL_KURULUS": 4,
    "GUNCEL_TURKIYE_KURULUS": 4,
    "GUNCEL_ONEMLI_TARIHLER": 4,
    "MAT_TEMEL_KAVRAMLAR": 4,
    "MAT_BOLUNEEBILME": 4,
    "MAT_ASAL_EBOB_EKOK": 4,
    "MAT_RASYONEL_SAYILAR": 4,
    "MAT_ESITSIZLIK_MUTLAK": 4,
    "MAT_USLU_SAYILAR": 4,
    "MAT_KOKLU_SAYILAR": 4,
    "MAT_ORAN_ORANTI": 4,
    "MAT_DENKLEM_PROBLEMLER": 4,
    "MAT_KUMELER": 4,
    "MAT_FONKSIYONLAR": 4,
    "MAT_PERMUTASYON_KOMBINASYON": 4,
    "MAT_OLASILIK_ISTATISTIK": 4,
    "MAT_ORUNTU_PROBLEMLERI": 4
  },
  "matching_games": {
    "JnFbEQt0uA8RSEuy22SQ": 1,
    "9Hg8tuMRdMTuVY7OZ9HL": 1,
    "8aIrKLvItXrwvOHq1L34": 1,
    "JU0iGKNhR7NQzA8M77vt": 1,
    "9WTotPoDW5OuWxsCf4Li": 1,
    "DlT19snCttf5j5RUAXLz": 1,
    "4GUvpqBBImcLmN2eh1HK": 1,
    "onwrfsH02TgIhlyRUh56": 1,
    "xQWHl1hBYAKM96X4deR8": 1,
    "80e0wkTLvaTQzPD6puB7": 1,
    "yWlh5C6jB7lzuJOodr2t": 1,
    "ICNDiSlTmmjWEQPT6rmT": 1,
    "JmyiPxf3n96Jkxqsa9jY": 1,
    "AJNLHhhaG2SLWOvxDYqW": 1,
    "nN8JOTR7LZm01AN2i3sQ": 1,
    "jXcsrl5HEb65DmfpfqqI": 1,
    "qSEqigIsIEBAkhcMTyCE": 1,
    "wnt2zWaV1pX8p8s8BBc9": 1,
    "1FEcPsGduhjcQARpaGBk": 1,
    "kbs0Ffved9pCP3Hq9M9k": 1,
    "6e0Thsz2RRNHFcwqQXso": 1,
    "uYDrMlBCEAho5776WZi8": 1,
    "WxrtQ26p2My4uJa0h1kk": 1,
    "GdpN8uxJNGtexWrkoL1T": 1,
    "AQ0Zph76dzPdr87H1uKa": 1,
    "n4OjWupHmouuybQzQ1Fc": 1,
    "xXGXiqx2TkCtI4C7GMQg": 1,
    "1JZAYECyEn7farNNyGyx": 1,
    "lv93cmhwq7RmOFM5WxWD": 1,
    "Bo3qqooJsqtIZrK5zc9S": 1,
    "GUNCEL_BM_KURULUS": 1,
    "GUNCEL_NATO_AB": 1,
    "GUNCEL_BOLGESEL_KURULUS": 1,
    "GUNCEL_TURKIYE_KURULUS": 1,
    "GUNCEL_ONEMLI_TARIHLER": 1,
    "MAT_TEMEL_KAVRAMLAR": 2,
    "MAT_BOLUNEEBILME": 2,
    "MAT_ASAL_EBOB_EKOK": 2,
    "MAT_RASYONEL_SAYILAR": 2,
    "MAT_ESITSIZLIK_MUTLAK": 3,
    "MAT_USLU_SAYILAR": 2,
    "MAT_KOKLU_SAYILAR": 2,
    "MAT_ORAN_ORANTI": 2,
    "MAT_DENKLEM_PROBLEMLER": 2,
    "MAT_KUMELER": 3,
    "MAT_FONKSIYONLAR": 3,
    "MAT_PERMUTASYON_KOMBINASYON": 3,
    "MAT_OLASILIK_ISTATISTIK": 2,
    "MAT_ORUNTU_PROBLEMLERI": 3
  },
  "lastUpdated": "2026-04-18T14:48:37.789Z",
  "all": {
    "1FEcPsGduhjcQARpaGBk": 1,
    "1JZAYECyEn7farNNyGyx": 1,
    "4GUvpqBBImcLmN2eh1HK": 1,
    "6e0Thsz2RRNHFcwqQXso": 1,
    "80e0wkTLvaTQzPD6puB7": 1,
    "8aIrKLvItXrwvOHq1L34": 1,
    "9Hg8tuMRdMTuVY7OZ9HL": 1,
    "9WTotPoDW5OuWxsCf4Li": 1,
    "AJNLHhhaG2SLWOvxDYqW": 1,
    "AQ0Zph76dzPdr87H1uKa": 1,
    "Bo3qqooJsqtIZrK5zc9S": 1,
    "DlT19snCttf5j5RUAXLz": 1,
    "GdpN8uxJNGtexWrkoL1T": 1,
    "ICNDiSlTmmjWEQPT6rmT": 1,
    "JmyiPxf3n96Jkxqsa9jY": 1,
    "JnFbEQt0uA8RSEuy22SQ": 1,
    "JU0iGKNhR7NQzA8M77vt": 1,
    "jXcsrl5HEb65DmfpfqqI": 1,
    "kbs0Ffved9pCP3Hq9M9k": 1,
    "lv93cmhwq7RmOFM5WxWD": 1,
    "mat_temel_001": 1,
    "n4OjWupHmouuybQzQ1Fc": 1,
    "nN8JOTR7LZm01AN2i3sQ": 1,
    "onwrfsH02TgIhlyRUh56": 1,
    "qSEqigIsIEBAkhcMTyCE": 1,
    "uYDrMlBCEAho5776WZi8": 1,
    "wnt2zWaV1pX8p8s8BBc9": 1,
    "WxrtQ26p2My4uJa0h1kk": 1,
    "xQWHl1hBYAKM96X4deR8": 1,
    "xXGXiqx2TkCtI4C7GMQg": 1,
    "yWlh5C6jB7lzuJOodr2t": 1
  },
  "last_updated": "2026-04-18T14:48:37.789Z",
  "productivity": {
    "motivation": 3,
    "timeManagement": 4,
    "breakGuide": 3,
    "concentration": 3,
    "examFastLearning": 3,
    "noteMemory": 3,
    "studyPlanning": 3
  },
  "glossary": {
    "1FEcPsGduhjcQARpaGBk": 1,
    "1JZAYECyEn7farNNyGyx": 1,
    "4GUvpqBBImcLmN2eh1HK": 1,
    "6e0Thsz2RRNHFcwqQXso": 1,
    "80e0wkTLvaTQzPD6puB7": 1,
    "8aIrKLvItXrwvOHq1L34": 1,
    "9Hg8tuMRdMTuVY7OZ9HL": 1,
    "9WTotPoDW5OuWxsCf4Li": 1,
    "AJNLHhhaG2SLWOvxDYqW": 1,
    "AQ0Zph76dzPdr87H1uKa": 1,
    "Bo3qqooJsqtIZrK5zc9S": 1,
    "DlT19snCttf5j5RUAXLz": 1,
    "GdpN8uxJNGtexWrkoL1T": 1,
    "GUNCEL_BM_KURULUS": 1,
    "GUNCEL_BOLGESEL_KURULUS": 1,
    "GUNCEL_NATO_AB": 1,
    "GUNCEL_ONEMLI_TARIHLER": 1,
    "GUNCEL_TURKIYE_KURULUS": 1,
    "ICNDiSlTmmjWEQPT6rmT": 1,
    "JmyiPxf3n96Jkxqsa9jY": 1,
    "JnFbEQt0uA8RSEuy22SQ": 1,
    "JU0iGKNhR7NQzA8M77vt": 1,
    "jXcsrl5HEb65DmfpfqqI": 1,
    "kbs0Ffved9pCP3Hq9M9k": 1,
    "lv93cmhwq7RmOFM5WxWD": 1,
    "MAT_ASAL_EBOB_EKOK": 1,
    "MAT_BOLUNEEBILME": 1,
    "MAT_DENKLEM_PROBLEMLER": 1,
    "MAT_ESITSIZLIK_MUTLAK": 1,
    "MAT_FONKSIYONLAR": 1,
    "MAT_KOKLU_SAYILAR": 1,
    "MAT_KUMELER": 1,
    "MAT_OLASILIK_ISTATISTIK": 1,
    "MAT_ORAN_ORANTI": 1,
    "MAT_ORUNTU_PROBLEMLERI": 1,
    "MAT_PERMUTASYON_KOMBINASYON": 1,
    "MAT_RASYONEL_SAYILAR": 1,
    "MAT_TEMEL_KAVRAMLAR": 1,
    "MAT_USLU_SAYILAR": 1,
    "n4OjWupHmouuybQzQ1Fc": 1,
    "nN8JOTR7LZm01AN2i3sQ": 1,
    "onwrfsH02TgIhlyRUh56": 1,
    "qSEqigIsIEBAkhcMTyCE": 1,
    "uYDrMlBCEAho5776WZi8": 1,
    "wnt2zWaV1pX8p8s8BBc9": 1,
    "WxrtQ26p2My4uJa0h1kk": 1,
    "xQWHl1hBYAKM96X4deR8": 1,
    "xXGXiqx2TkCtI4C7GMQg": 1,
    "yWlh5C6jB7lzuJOodr2t": 1
  }
}