[
  {
    "topicId": "qSEqigIsIEBAkhcMTyCE",
    "question": "De da bağlacı",
    "answer": "Her zaman ayrı yazılır",
    "id": "match_1",
    "_part": 1,
    "_generatedAt": "2026-04-12T17:41:53.593Z"
  },
  {
    "topicId": "qSEqigIsIEBAkhcMTyCE",
    "question": "Mi soru eki",
    "answer": "Her zaman ayrı yazılır",
    "id": "match_2",
    "_part": 2,
    "_generatedAt": "2026-04-12T17:41:53.593Z"
  },
  {
    "topicId": "qSEqigIsIEBAkhcMTyCE",
    "question": "Ki bağlacı",
    "answer": "Her zaman ayrı yazılır",
    "id": "match_3",
    "_part": 3,
    "_generatedAt": "2026-04-12T17:41:53.593Z"
  },
  {
    "topicId": "qSEqigIsIEBAkhcMTyCE",
    "question": "İkilemeler",
    "answer": "Her zaman ayrı yazılır",
    "id": "match_4",
    "_part": 4,
    "_generatedAt": "2026-04-12T17:41:53.593Z"
  },
  {
    "topicId": "qSEqigIsIEBAkhcMTyCE",
    "question": "Alt, üst, üzeri sözleri",
    "answer": "Somut yer bildirmiyorsa bitişik yazılır",
    "id": "match_5",
    "_part": 5,
    "_generatedAt": "2026-04-12T17:41:53.593Z"
  },
  {
    "topicId": "qSEqigIsIEBAkhcMTyCE",
    "question": "Kurallı birleşik fiiller",
    "answer": "Her zaman bitişik yazılır",
    "id": "match_6",
    "_part": 6,
    "_generatedAt": "2026-04-12T17:41:53.593Z"
  },
  {
    "topicId": "qSEqigIsIEBAkhcMTyCE",
    "question": "Yön isimleri",
    "answer": "Özel isimden önce gelirse büyük harfle başlar",
    "id": "match_7",
    "_part": 7,
    "_generatedAt": "2026-04-12T17:41:53.593Z"
  },
  {
    "topicId": "qSEqigIsIEBAkhcMTyCE",
    "question": "Virgül kullanımı",
    "answer": "Metin içinde art arda gelen zarf-fiil eklerinden sonra kullanılmaz",
    "id": "match_8",
    "_part": 8,
    "_generatedAt": "2026-04-12T17:41:53.593Z"
  },
  {
    "topicId": "qSEqigIsIEBAkhcMTyCE",
    "question": "Noktalı virgül",
    "answer": "Ögeleri arasında virgül bulunan sıralı cümleleri ayırır",
    "id": "match_9",
    "_part": 9,
    "_generatedAt": "2026-04-12T17:41:53.593Z"
  },
  {
    "topicId": "qSEqigIsIEBAkhcMTyCE",
    "question": "İki nokta",
    "answer": "Kendisiyle ilgili örnek verilecek cümlenin sonuna konur",
    "id": "match_10",
    "_part": 10,
    "_generatedAt": "2026-04-12T17:41:53.593Z"
  },
  {
    "topicId": "qSEqigIsIEBAkhcMTyCE",
    "question": "Üç nokta",
    "answer": "Anlatım olarak tamamlanmamış cümlelerin sonuna konur",
    "id": "match_11",
    "_part": 11,
    "_generatedAt": "2026-04-12T17:41:53.593Z"
  },
  {
    "topicId": "qSEqigIsIEBAkhcMTyCE",
    "question": "Kısa çizgi",
    "answer": "Satıra sığmayan kelimeleri bölmek için kullanılır",
    "id": "match_12",
    "_part": 12,
    "_generatedAt": "2026-04-12T17:41:53.593Z"
  },
  {
    "topicId": "qSEqigIsIEBAkhcMTyCE",
    "question": "Kesme işareti",
    "answer": "Özel isimlere getirilen çekim eklerini ayırır",
    "id": "match_13",
    "_part": 13,
    "_generatedAt": "2026-04-12T17:41:53.593Z"
  },
  {
    "topicId": "qSEqigIsIEBAkhcMTyCE",
    "question": "Tırnak işareti",
    "answer": "Başka bir kimseden aktarılan sözler için kullanılır",
    "id": "match_14",
    "_part": 14,
    "_generatedAt": "2026-04-12T17:41:53.593Z"
  },
  {
    "topicId": "qSEqigIsIEBAkhcMTyCE",
    "question": "Yay ayraç",
    "answer": "Cümlenin yapısıyla doğrudan ilgili olmayan açıklamalar için kullanılır",
    "id": "match_15",
    "_part": 15,
    "_generatedAt": "2026-04-12T17:41:53.593Z"
  },
  {
    "topicId": "qSEqigIsIEBAkhcMTyCE",
    "question": "Unvanlar",
    "answer": "Kişi adlarından önce veya sonra gelenler büyük harfle başlar",
    "id": "match_16",
    "_part": 16,
    "_generatedAt": "2026-04-12T17:41:53.593Z"
  },
  {
    "topicId": "qSEqigIsIEBAkhcMTyCE",
    "question": "Sayıların yazımı",
    "answer": "Saat ve dakikalar metin içinde yazıyla gösterilir",
    "id": "match_17",
    "_part": 17,
    "_generatedAt": "2026-04-12T17:41:53.593Z"
  },
  {
    "topicId": "qSEqigIsIEBAkhcMTyCE",
    "question": "Etmek, olmak yardımcı fiilleri",
    "answer": "Ses düşmesi veya türemesi varsa bitişik yazılır",
    "id": "match_18",
    "_part": 18,
    "_generatedAt": "2026-04-12T17:41:53.593Z"
  },
  {
    "topicId": "qSEqigIsIEBAkhcMTyCE",
    "question": "Soru işareti",
    "answer": "Bilinmeyen yer, tarih vb. durumlar için kullanılır",
    "id": "match_19",
    "_part": 19,
    "_generatedAt": "2026-04-12T17:41:53.593Z"
  },
  {
    "topicId": "qSEqigIsIEBAkhcMTyCE",
    "question": "Ünlem işareti",
    "answer": "Seslenme, hitap ve uyarı sözlerinden sonra konur",
    "id": "match_20",
    "_part": 20,
    "_generatedAt": "2026-04-12T17:41:53.593Z"
  }
]